chand/__init__.py
chand/api.py
chand/chand.py
chand/coins.py
chand-0.0.2.dist-info/LICENSE
chand-0.0.2.dist-info/METADATA
chand-0.0.2.dist-info/WHEEL
chand-0.0.2.dist-info/top_level.txt
chand-0.0.2.dist-info/RECORD
