Metadata-Version: 2.1
Name: chand
Version: 0.0.2
Summary: A Python library for converting currencies to Iranian Rial and Toman.
Home-page: https://github.com/armanyazdi/chand
Author: Arman Yazdi
License: MIT
Project-URL: Source, https://github.com/armanyazdi/chand
Project-URL: Documentation, https://pypi.org/project/chand
Keywords: currency converter,crypto converter,iranian rial,iranian toman
Platform: UNKNOWN
Classifier: License :: OSI Approved :: MIT License
Classifier: Natural Language :: Persian
Classifier: Natural Language :: English
Classifier: Programming Language :: Python
Classifier: Programming Language :: Python :: 3.6
Classifier: Programming Language :: Python :: 3.7
Classifier: Programming Language :: Python :: 3.8
Classifier: Programming Language :: Python :: 3.9
Classifier: Programming Language :: Python :: 3.10
Classifier: Programming Language :: Python :: 3.11
Classifier: Topic :: Software Development :: Libraries
Classifier: Topic :: Software Development :: Libraries :: Python Modules
Classifier: Topic :: Software Development :: Localization
Requires-Python: >= 3.6
License-File: LICENSE
Requires-Dist: requests
Requires-Dist: bs4
